runbooks/__init__.py
runbooks/__init___optimized.py
runbooks/__main__.py
runbooks/base.py
runbooks/config.py
runbooks/main.py
runbooks/_platform/__init__.py
runbooks/_platform/core/runbooks_wrapper.py
runbooks/aws2/accuracy_validator.py
runbooks/cfat/README.md
runbooks/cfat/WEIGHT_CONFIG_README.md
runbooks/cfat/__init__.py
runbooks/cfat/app.ts
runbooks/cfat/asana-import.csv
runbooks/cfat/assessment.zip
runbooks/cfat/cfat-checks.csv
runbooks/cfat/cfat.txt
runbooks/cfat/cli.py
runbooks/cfat/cloud_foundations_assessment.py
runbooks/cfat/jira-import.csv
runbooks/cfat/models.py
runbooks/cfat/package-lock.json
runbooks/cfat/package.json
runbooks/cfat/report.py
runbooks/cfat/run-assessment.sh
runbooks/cfat/runner.py
runbooks/cfat/tsconfig.json
runbooks/cfat/webpack.config.cjs
runbooks/cfat/weight_config.ts
runbooks/cfat/assessment/__init__.py
runbooks/cfat/assessment/asana-import.csv
runbooks/cfat/assessment/cfat-checks.csv
runbooks/cfat/assessment/cfat.txt
runbooks/cfat/assessment/collectors.py
runbooks/cfat/assessment/compliance.py
runbooks/cfat/assessment/jira-import.csv
runbooks/cfat/assessment/runner.py
runbooks/cfat/assessment/validators.py
runbooks/cfat/cfat/asana-import.csv
runbooks/cfat/cfat/assessment.zip
runbooks/cfat/cfat/cfat-checks.csv
runbooks/cfat/cfat/cfat.txt
runbooks/cfat/cfat/jira-import.csv
runbooks/cfat/docs/asana-import.csv
runbooks/cfat/docs/cfat-checks.csv
runbooks/cfat/docs/cfat.txt
runbooks/cfat/docs/checks-output.png
runbooks/cfat/docs/cloudshell-console-run.png
runbooks/cfat/docs/cloudshell-download.png
runbooks/cfat/docs/cloudshell-output.png
runbooks/cfat/docs/downloadfile.png
runbooks/cfat/docs/jira-import.csv
runbooks/cfat/docs/open-cloudshell.png
runbooks/cfat/docs/report-header.png
runbooks/cfat/reporting/__init__.py
runbooks/cfat/reporting/exporters.py
runbooks/cfat/reporting/formatters.py
runbooks/cfat/reporting/templates.py
runbooks/cfat/src/actions/check-cloudtrail-existence.ts
runbooks/cfat/src/actions/check-config-existence.ts
runbooks-1.3.0.dist-info/licenses/LICENSE
runbooks-1.3.0.dist-info/METADATA
runbooks-1.3.0.dist-info/WHEEL
runbooks-1.3.0.dist-info/entry_points.txt
runbooks-1.3.0.dist-info/top_level.txt
runbooks-1.3.0.dist-info/RECORD
