Metadata-Version: 2.4
Name: runbooks
Version: 1.3.0
Summary: CloudOps Automation Toolkit with Enhanced Cloud Foundations Assessment for DevOps and SRE teams.
Author-email: Maintainers <nnthanh101@gmail.com>
License-Expression: Apache-2.0
Project-URL: Homepage, https://cloudops.oceansoft.io
Project-URL: Repository, https://github.com/1xOps/CloudOps-Runbooks
Project-URL: Documentation, https://cloudops.oceansoft.io/runbooks/
Project-URL: Issues, https://github.com/1xOps/CloudOps-Runbooks/issues
Project-URL: Changelog, https://github.com/1xOps/CloudOps-Runbooks/blob/main/CHANGELOG.md
Keywords: runbooks,automation,DevOps,SRE,CloudOps,AWS,cloud-foundations,FinOps,enterprise,cost-optimization,security-compliance,multi-account,business-intelligence
Classifier: Development Status :: 5 - Production/Stable
Classifier: Environment :: Console
Classifier: Operating System :: OS Independent
Classifier: Programming Language :: Python :: 3
Classifier: Programming Language :: Python :: 3.11
Classifier: Programming Language :: Python :: 3.12
Classifier: Programming Language :: Python :: 3.13
Classifier: Topic :: System :: Systems Administration
Classifier: Topic :: Software Development :: Libraries :: Python Modules
Classifier: Topic :: Utilities
Requires-Python: <3.14,>=3.11
License-File: LICENSE
Requires-Dist: boto3>=1.35.40
Requires-Dist: botocore>=1.35.40
Requires-Dist: diagrams>=0.24.4
Requires-Dist: click>=8.2.1
Requires-Dist: pydantic>=2.10.0
Requires-Dist: pydantic-settings>=2.0.0
Requires-Dist: jinja2>=3.1.4
Requires-Dist: werkzeug>=3.1.0
Requires-Dist: markdown>=3.7.0
Requires-Dist: simplejson>=3.20.1
Requires-Dist: python-dateutil>=2.9.0
Requires-Dist: loguru>=0.7.3
Requires-Dist: graphviz>=0.20.1
Requires-Dist: rich>=14.1.0
Requires-Dist: reportlab>=3.6.1
Requires-Dist: requests>=2.32.0
Requires-Dist: packaging>=21.0
Requires-Dist: pyyaml>=6.0.2
Requires-Dist: jmespath>=1.0.1
Requires-Dist: urllib3<1.27,>=1.26.18
Requires-Dist: openapi-spec-validator>=0.7.2
Requires-Dist: mcp>=1.12.3
Requires-Dist: pandas>=2.3.1
Requires-Dist: ipython>=9.4.0
Requires-Dist: psutil>=7.0.0
Requires-Dist: matplotlib>=3.10.5
Requires-Dist: seaborn>=0.13.2
Requires-Dist: plotly>=6.3.0
Requires-Dist: papermill>=2.6.0
Requires-Dist: jupyter>=1.1.1
Requires-Dist: ipywidgets>=8.1.7
Requires-Dist: pytest>=8.4.1
Requires-Dist: scipy>=1.16.2
Requires-Dist: pytest-bdd>=8.1.0
Requires-Dist: xlsxwriter>=3.2.9
Requires-Dist: tabulate>=0.9.0
Requires-Dist: typer>=0.21.1
Requires-Dist: openpyxl>=3.1.5
Dynamic: license-file
